xy_settings/Settings.py
xy_settings/SettingsDelegate.py
xy_settings/__init__.py
xy_settings/Section/Section.py
xy_settings/Section/__init__.py
xy_settings-1.0.6.dist-info/LICENSE
xy_settings-1.0.6.dist-info/METADATA
xy_settings-1.0.6.dist-info/WHEEL
xy_settings-1.0.6.dist-info/top_level.txt
xy_settings-1.0.6.dist-info/RECORD
