Metadata-Version: 2.1
Name: xy_settings
Version: 1.0.6
Summary: 项目设置模块
Author-email: 余洋 <yuyangit.0515@qq.com>
Classifier: Programming Language :: Python :: 3
Requires-Python: >=3.11.3
License-File: LICENSE
Requires-Dist: xy_type
Requires-Dist: xy_string
Requires-Dist: xy_file
Requires-Dist: xy_configure
